[
  {
    "url": "https://api.github.com/repos/bookdash/bookdash-android-app/releases/22859009",
    "assets_url": "https://api.github.com/repos/bookdash/bookdash-android-app/releases/22859009/assets",
    "upload_url": "https://uploads.github.com/repos/bookdash/bookdash-android-app/releases/22859009/assets{?name,label}",
    "html_url": "https://github.com/bookdash/bookdash-android-app/releases/tag/2.8.0",
    "id": 22859009,
    "node_id": "MDc6UmVsZWFzZTIyODU5MDA5",
    "tag_name": "2.8.0",
    "target_commitish": "master",
    "name": "Bug Fixes and Android X Upgrades",
    "draft": false,
    "author": {
      "login": "riggaroo",
      "id": 9973046,
      "node_id": "MDQ6VXNlcjk5NzMwNDY=",
      "avatar_url": "https://avatars0.githubusercontent.com/u/9973046?v=4",
      "gravatar_id": "",
      "url": "https://api.github.com/users/riggaroo",
      "html_url": "https://github.com/riggaroo",
      "followers_url": "https://api.github.com/users/riggaroo/followers",
      "following_url": "https://api.github.com/users/riggaroo/following{/other_user}",
      "gists_url": "https://api.github.com/users/riggaroo/gists{/gist_id}",
      "starred_url": "https://api.github.com/users/riggaroo/starred{/owner}{/repo}",
      "subscriptions_url": "https://api.github.com/users/riggaroo/subscriptions",
      "organizations_url": "https://api.github.com/users/riggaroo/orgs",
      "repos_url": "https://api.github.com/users/riggaroo/repos",
      "events_url": "https://api.github.com/users/riggaroo/events{/privacy}",
      "received_events_url": "https://api.github.com/users/riggaroo/received_events",
      "type": "User",
      "site_admin": false
    },
    "prerelease": false,
    "created_at": "2020-01-15T13:37:48Z",
    "published_at": "2020-01-15T13:39:59Z",
    "assets": [
      {
        "url": "https://api.github.com/repos/bookdash/bookdash-android-app/releases/assets/20472529",
        "id": 20472529,
        "node_id": "MDEyOlJlbGVhc2VBc3NldDIwNDcyNTI5",
        "name": "book_dash_2_8_0.apk",
        "label": null,
        "uploader": {
          "login": "HeinrichWesson",
          "id": 16528836,
          "node_id": "MDQ6VXNlcjE2NTI4ODM2",
          "avatar_url": "https://avatars2.githubusercontent.com/u/16528836?v=4",
          "gravatar_id": "",
          "url": "https://api.github.com/users/HeinrichWesson",
          "html_url": "https://github.com/HeinrichWesson",
          "followers_url": "https://api.github.com/users/HeinrichWesson/followers",
          "following_url": "https://api.github.com/users/HeinrichWesson/following{/other_user}",
          "gists_url": "https://api.github.com/users/HeinrichWesson/gists{/gist_id}",
          "starred_url": "https://api.github.com/users/HeinrichWesson/starred{/owner}{/repo}",
          "subscriptions_url": "https://api.github.com/users/HeinrichWesson/subscriptions",
          "organizations_url": "https://api.github.com/users/HeinrichWesson/orgs",
          "repos_url": "https://api.github.com/users/HeinrichWesson/repos",
          "events_url": "https://api.github.com/users/HeinrichWesson/events{/privacy}",
          "received_events_url": "https://api.github.com/users/HeinrichWesson/received_events",
          "type": "User",
          "site_admin": false
        },
        "content_type": "application/vnd.android.package-archive",
        "state": "uploaded",
        "size": 4834150,
        "download_count": 4,
        "created_at": "2020-05-06T12:47:00Z",
        "updated_at": "2020-05-06T12:47:30Z",
        "browser_download_url": "https://github.com/bookdash/bookdash-android-app/releases/download/2.8.0/book_dash_2_8_0.apk"
      }
    ],
    "tarball_url": "https://api.github.com/repos/bookdash/bookdash-android-app/tarball/2.8.0",
    "zipball_url": "https://api.github.com/repos/bookdash/bookdash-android-app/zipball/2.8.0",
    "body": "Android X Upgrades\r\nFirebase Invite removal\r\nBug fixes"
  },
  {
    "url": "https://api.github.com/repos/bookdash/bookdash-android-app/releases/9721464",
    "assets_url": "https://api.github.com/repos/bookdash/bookdash-android-app/releases/9721464/assets",
    "upload_url": "https://uploads.github.com/repos/bookdash/bookdash-android-app/releases/9721464/assets{?name,label}",
    "html_url": "https://github.com/bookdash/bookdash-android-app/releases/tag/Release-2.7.0",
    "id": 9721464,
    "node_id": "MDc6UmVsZWFzZTk3MjE0NjQ=",
    "tag_name": "Release-2.7.0",
    "target_commitish": "master",
    "name": "Including FIrebase Perf and updated libraries of things",
    "draft": false,
    "author": {
      "login": "riggaroo",
      "id": 9973046,
      "node_id": "MDQ6VXNlcjk5NzMwNDY=",
      "avatar_url": "https://avatars0.githubusercontent.com/u/9973046?v=4",
      "gravatar_id": "",
      "url": "https://api.github.com/users/riggaroo",
      "html_url": "https://github.com/riggaroo",
      "followers_url": "https://api.github.com/users/riggaroo/followers",
      "following_url": "https://api.github.com/users/riggaroo/following{/other_user}",
      "gists_url": "https://api.github.com/users/riggaroo/gists{/gist_id}",
      "starred_url": "https://api.github.com/users/riggaroo/starred{/owner}{/repo}",
      "subscriptions_url": "https://api.github.com/users/riggaroo/subscriptions",
      "organizations_url": "https://api.github.com/users/riggaroo/orgs",
      "repos_url": "https://api.github.com/users/riggaroo/repos",
      "events_url": "https://api.github.com/users/riggaroo/events{/privacy}",
      "received_events_url": "https://api.github.com/users/riggaroo/received_events",
      "type": "User",
      "site_admin": false
    },
    "prerelease": false,
    "created_at": "2018-02-17T20:29:43Z",
    "published_at": "2018-02-17T20:40:29Z",
    "assets": [
      {
        "url": "https://api.github.com/repos/bookdash/bookdash-android-app/releases/assets/6245016",
        "id": 6245016,
        "node_id": "MDEyOlJlbGVhc2VBc3NldDYyNDUwMTY=",
        "name": "app-prod-release.apk",
        "label": null,
        "uploader": {
          "login": "riggaroo",
          "id": 9973046,
          "node_id": "MDQ6VXNlcjk5NzMwNDY=",
          "avatar_url": "https://avatars0.githubusercontent.com/u/9973046?v=4",
          "gravatar_id": "",
          "url": "https://api.github.com/users/riggaroo",
          "html_url": "https://github.com/riggaroo",
          "followers_url": "https://api.github.com/users/riggaroo/followers",
          "following_url": "https://api.github.com/users/riggaroo/following{/other_user}",
          "gists_url": "https://api.github.com/users/riggaroo/gists{/gist_id}",
          "starred_url": "https://api.github.com/users/riggaroo/starred{/owner}{/repo}",
          "subscriptions_url": "https://api.github.com/users/riggaroo/subscriptions",
          "organizations_url": "https://api.github.com/users/riggaroo/orgs",
          "repos_url": "https://api.github.com/users/riggaroo/repos",
          "events_url": "https://api.github.com/users/riggaroo/events{/privacy}",
          "received_events_url": "https://api.github.com/users/riggaroo/received_events",
          "type": "User",
          "site_admin": false
        },
        "content_type": "application/vnd.android.package-archive",
        "state": "uploaded",
        "size": 4366305,
        "download_count": 45,
        "created_at": "2018-02-17T20:40:14Z",
        "updated_at": "2018-02-17T20:40:27Z",
        "browser_download_url": "https://github.com/bookdash/bookdash-android-app/releases/download/Release-2.7.0/app-prod-release.apk"
      }
    ],
    "tarball_url": "https://api.github.com/repos/bookdash/bookdash-android-app/tarball/Release-2.7.0",
    "zipball_url": "https://api.github.com/repos/bookdash/bookdash-android-app/zipball/Release-2.7.0",
    "body": ""
  },
  {
    "url": "https://api.github.com/repos/bookdash/bookdash-android-app/releases/3138652",
    "assets_url": "https://api.github.com/repos/bookdash/bookdash-android-app/releases/3138652/assets",
    "upload_url": "https://uploads.github.com/repos/bookdash/bookdash-android-app/releases/3138652/assets{?name,label}",
    "html_url": "https://github.com/bookdash/bookdash-android-app/releases/tag/Release-1.1.2",
    "id": 3138652,
    "node_id": "MDc6UmVsZWFzZTMxMzg2NTI=",
    "tag_name": "Release-1.1.2",
    "target_commitish": "master",
    "name": "",
    "draft": false,
    "author": {
      "login": "riggaroo",
      "id": 9973046,
      "node_id": "MDQ6VXNlcjk5NzMwNDY=",
      "avatar_url": "https://avatars0.githubusercontent.com/u/9973046?v=4",
      "gravatar_id": "",
      "url": "https://api.github.com/users/riggaroo",
      "html_url": "https://github.com/riggaroo",
      "followers_url": "https://api.github.com/users/riggaroo/followers",
      "following_url": "https://api.github.com/users/riggaroo/following{/other_user}",
      "gists_url": "https://api.github.com/users/riggaroo/gists{/gist_id}",
      "starred_url": "https://api.github.com/users/riggaroo/starred{/owner}{/repo}",
      "subscriptions_url": "https://api.github.com/users/riggaroo/subscriptions",
      "organizations_url": "https://api.github.com/users/riggaroo/orgs",
      "repos_url": "https://api.github.com/users/riggaroo/repos",
      "events_url": "https://api.github.com/users/riggaroo/events{/privacy}",
      "received_events_url": "https://api.github.com/users/riggaroo/received_events",
      "type": "User",
      "site_admin": false
    },
    "prerelease": false,
    "created_at": "2016-05-02T08:43:37Z",
    "published_at": "2016-05-02T08:54:30Z",
    "assets": [
      {
        "url": "https://api.github.com/repos/bookdash/bookdash-android-app/releases/assets/1626766",
        "id": 1626766,
        "node_id": "MDEyOlJlbGVhc2VBc3NldDE2MjY3NjY=",
        "name": "app-prod-release.apk",
        "label": null,
        "uploader": {
          "login": "riggaroo",
          "id": 9973046,
          "node_id": "MDQ6VXNlcjk5NzMwNDY=",
          "avatar_url": "https://avatars0.githubusercontent.com/u/9973046?v=4",
          "gravatar_id": "",
          "url": "https://api.github.com/users/riggaroo",
          "html_url": "https://github.com/riggaroo",
          "followers_url": "https://api.github.com/users/riggaroo/followers",
          "following_url": "https://api.github.com/users/riggaroo/following{/other_user}",
          "gists_url": "https://api.github.com/users/riggaroo/gists{/gist_id}",
          "starred_url": "https://api.github.com/users/riggaroo/starred{/owner}{/repo}",
          "subscriptions_url": "https://api.github.com/users/riggaroo/subscriptions",
          "organizations_url": "https://api.github.com/users/riggaroo/orgs",
          "repos_url": "https://api.github.com/users/riggaroo/repos",
          "events_url": "https://api.github.com/users/riggaroo/events{/privacy}",
          "received_events_url": "https://api.github.com/users/riggaroo/received_events",
          "type": "User",
          "site_admin": false
        },
        "content_type": "application/vnd.android.package-archive",
        "state": "uploaded",
        "size": 3946844,
        "download_count": 22,
        "created_at": "2016-05-02T08:52:20Z",
        "updated_at": "2016-05-02T08:54:22Z",
        "browser_download_url": "https://github.com/bookdash/bookdash-android-app/releases/download/Release-1.1.2/app-prod-release.apk"
      }
    ],
    "tarball_url": "https://api.github.com/repos/bookdash/bookdash-android-app/tarball/Release-1.1.2",
    "zipball_url": "https://api.github.com/repos/bookdash/bookdash-android-app/zipball/Release-1.1.2",
    "body": ""
  },
  {
    "url": "https://api.github.com/repos/bookdash/bookdash-android-app/releases/3085602",
    "assets_url": "https://api.github.com/repos/bookdash/bookdash-android-app/releases/3085602/assets",
    "upload_url": "https://uploads.github.com/repos/bookdash/bookdash-android-app/releases/3085602/assets{?name,label}",
    "html_url": "https://github.com/bookdash/bookdash-android-app/releases/tag/Release-1.1.0",
    "id": 3085602,
    "node_id": "MDc6UmVsZWFzZTMwODU2MDI=",
    "tag_name": "Release-1.1.0",
    "target_commitish": "master",
    "name": "v1.1.0",
    "draft": false,
    "author": {
      "login": "riggaroo",
      "id": 9973046,
      "node_id": "MDQ6VXNlcjk5NzMwNDY=",
      "avatar_url": "https://avatars0.githubusercontent.com/u/9973046?v=4",
      "gravatar_id": "",
      "url": "https://api.github.com/users/riggaroo",
      "html_url": "https://github.com/riggaroo",
      "followers_url": "https://api.github.com/users/riggaroo/followers",
      "following_url": "https://api.github.com/users/riggaroo/following{/other_user}",
      "gists_url": "https://api.github.com/users/riggaroo/gists{/gist_id}",
      "starred_url": "https://api.github.com/users/riggaroo/starred{/owner}{/repo}",
      "subscriptions_url": "https://api.github.com/users/riggaroo/subscriptions",
      "organizations_url": "https://api.github.com/users/riggaroo/orgs",
      "repos_url": "https://api.github.com/users/riggaroo/repos",
      "events_url": "https://api.github.com/users/riggaroo/events{/privacy}",
      "received_events_url": "https://api.github.com/users/riggaroo/received_events",
      "type": "User",
      "site_admin": false
    },
    "prerelease": false,
    "created_at": "2016-04-24T09:57:52Z",
    "published_at": "2016-04-24T10:01:29Z",
    "assets": [
      {
        "url": "https://api.github.com/repos/bookdash/bookdash-android-app/releases/assets/1591512",
        "id": 1591512,
        "node_id": "MDEyOlJlbGVhc2VBc3NldDE1OTE1MTI=",
        "name": "app-prod-release.apk",
        "label": null,
        "uploader": {
          "login": "riggaroo",
          "id": 9973046,
          "node_id": "MDQ6VXNlcjk5NzMwNDY=",
          "avatar_url": "https://avatars0.githubusercontent.com/u/9973046?v=4",
          "gravatar_id": "",
          "url": "https://api.github.com/users/riggaroo",
          "html_url": "https://github.com/riggaroo",
          "followers_url": "https://api.github.com/users/riggaroo/followers",
          "following_url": "https://api.github.com/users/riggaroo/following{/other_user}",
          "gists_url": "https://api.github.com/users/riggaroo/gists{/gist_id}",
          "starred_url": "https://api.github.com/users/riggaroo/starred{/owner}{/repo}",
          "subscriptions_url": "https://api.github.com/users/riggaroo/subscriptions",
          "organizations_url": "https://api.github.com/users/riggaroo/orgs",
          "repos_url": "https://api.github.com/users/riggaroo/repos",
          "events_url": "https://api.github.com/users/riggaroo/events{/privacy}",
          "received_events_url": "https://api.github.com/users/riggaroo/received_events",
          "type": "User",
          "site_admin": false
        },
        "content_type": "application/vnd.android.package-archive",
        "state": "uploaded",
        "size": 3738197,
        "download_count": 15,
        "created_at": "2016-04-24T10:00:13Z",
        "updated_at": "2016-04-24T10:01:00Z",
        "browser_download_url": "https://github.com/bookdash/bookdash-android-app/releases/download/Release-1.1.0/app-prod-release.apk"
      }
    ],
    "tarball_url": "https://api.github.com/repos/bookdash/bookdash-android-app/tarball/Release-1.1.0",
    "zipball_url": "https://api.github.com/repos/bookdash/bookdash-android-app/zipball/Release-1.1.0",
    "body": "Added the ability to delete a download\nSome UI Tweaks\nSome bug fixes.\n"
  },
  {
    "url": "https://api.github.com/repos/bookdash/bookdash-android-app/releases/2567741",
    "assets_url": "https://api.github.com/repos/bookdash/bookdash-android-app/releases/2567741/assets",
    "upload_url": "https://uploads.github.com/repos/bookdash/bookdash-android-app/releases/2567741/assets{?name,label}",
    "html_url": "https://github.com/bookdash/bookdash-android-app/releases/tag/v1.0.13",
    "id": 2567741,
    "node_id": "MDc6UmVsZWFzZTI1Njc3NDE=",
    "tag_name": "v1.0.13",
    "target_commitish": "master",
    "name": "v1.0.13",
    "draft": false,
    "author": {
      "login": "riggaroo",
      "id": 9973046,
      "node_id": "MDQ6VXNlcjk5NzMwNDY=",
      "avatar_url": "https://avatars0.githubusercontent.com/u/9973046?v=4",
      "gravatar_id": "",
      "url": "https://api.github.com/users/riggaroo",
      "html_url": "https://github.com/riggaroo",
      "followers_url": "https://api.github.com/users/riggaroo/followers",
      "following_url": "https://api.github.com/users/riggaroo/following{/other_user}",
      "gists_url": "https://api.github.com/users/riggaroo/gists{/gist_id}",
      "starred_url": "https://api.github.com/users/riggaroo/starred{/owner}{/repo}",
      "subscriptions_url": "https://api.github.com/users/riggaroo/subscriptions",
      "organizations_url": "https://api.github.com/users/riggaroo/orgs",
      "repos_url": "https://api.github.com/users/riggaroo/repos",
      "events_url": "https://api.github.com/users/riggaroo/events{/privacy}",
      "received_events_url": "https://api.github.com/users/riggaroo/received_events",
      "type": "User",
      "site_admin": false
    },
    "prerelease": false,
    "created_at": "2016-02-07T09:02:44Z",
    "published_at": "2016-02-07T09:06:21Z",
    "assets": [
      {
        "url": "https://api.github.com/repos/bookdash/bookdash-android-app/releases/assets/1285632",
        "id": 1285632,
        "node_id": "MDEyOlJlbGVhc2VBc3NldDEyODU2MzI=",
        "name": "app-prod-release.apk",
        "label": null,
        "uploader": {
          "login": "riggaroo",
          "id": 9973046,
          "node_id": "MDQ6VXNlcjk5NzMwNDY=",
          "avatar_url": "https://avatars0.githubusercontent.com/u/9973046?v=4",
          "gravatar_id": "",
          "url": "https://api.github.com/users/riggaroo",
          "html_url": "https://github.com/riggaroo",
          "followers_url": "https://api.github.com/users/riggaroo/followers",
          "following_url": "https://api.github.com/users/riggaroo/following{/other_user}",
          "gists_url": "https://api.github.com/users/riggaroo/gists{/gist_id}",
          "starred_url": "https://api.github.com/users/riggaroo/starred{/owner}{/repo}",
          "subscriptions_url": "https://api.github.com/users/riggaroo/subscriptions",
          "organizations_url": "https://api.github.com/users/riggaroo/orgs",
          "repos_url": "https://api.github.com/users/riggaroo/repos",
          "events_url": "https://api.github.com/users/riggaroo/events{/privacy}",
          "received_events_url": "https://api.github.com/users/riggaroo/received_events",
          "type": "User",
          "site_admin": false
        },
        "content_type": "application/vnd.android.package-archive",
        "state": "uploaded",
        "size": 3688691,
        "download_count": 14,
        "created_at": "2016-02-07T09:05:44Z",
        "updated_at": "2016-02-07T09:06:18Z",
        "browser_download_url": "https://github.com/bookdash/bookdash-android-app/releases/download/v1.0.13/app-prod-release.apk"
      }
    ],
    "tarball_url": "https://api.github.com/repos/bookdash/bookdash-android-app/tarball/v1.0.13",
    "zipball_url": "https://api.github.com/repos/bookdash/bookdash-android-app/zipball/v1.0.13",
    "body": "Bug fix for crash on Book Information.\n"
  },
  {
    "url": "https://api.github.com/repos/bookdash/bookdash-android-app/releases/2365372",
    "assets_url": "https://api.github.com/repos/bookdash/bookdash-android-app/releases/2365372/assets",
    "upload_url": "https://uploads.github.com/repos/bookdash/bookdash-android-app/releases/2365372/assets{?name,label}",
    "html_url": "https://github.com/bookdash/bookdash-android-app/releases/tag/v1.0.12",
    "id": 2365372,
    "node_id": "MDc6UmVsZWFzZTIzNjUzNzI=",
    "tag_name": "v1.0.12",
    "target_commitish": "master",
    "name": "v1.0.12 - Side Navigation",
    "draft": false,
    "author": {
      "login": "riggaroo",
      "id": 9973046,
      "node_id": "MDQ6VXNlcjk5NzMwNDY=",
      "avatar_url": "https://avatars0.githubusercontent.com/u/9973046?v=4",
      "gravatar_id": "",
      "url": "https://api.github.com/users/riggaroo",
      "html_url": "https://github.com/riggaroo",
      "followers_url": "https://api.github.com/users/riggaroo/followers",
      "following_url": "https://api.github.com/users/riggaroo/following{/other_user}",
      "gists_url": "https://api.github.com/users/riggaroo/gists{/gist_id}",
      "starred_url": "https://api.github.com/users/riggaroo/starred{/owner}{/repo}",
      "subscriptions_url": "https://api.github.com/users/riggaroo/subscriptions",
      "organizations_url": "https://api.github.com/users/riggaroo/orgs",
      "repos_url": "https://api.github.com/users/riggaroo/repos",
      "events_url": "https://api.github.com/users/riggaroo/events{/privacy}",
      "received_events_url": "https://api.github.com/users/riggaroo/received_events",
      "type": "User",
      "site_admin": false
    },
    "prerelease": false,
    "created_at": "2016-01-03T16:44:11Z",
    "published_at": "2016-01-03T16:53:43Z",
    "assets": [
      {
        "url": "https://api.github.com/repos/bookdash/bookdash-android-app/releases/assets/1172782",
        "id": 1172782,
        "node_id": "MDEyOlJlbGVhc2VBc3NldDExNzI3ODI=",
        "name": "app-prod-release.apk",
        "label": null,
        "uploader": {
          "login": "riggaroo",
          "id": 9973046,
          "node_id": "MDQ6VXNlcjk5NzMwNDY=",
          "avatar_url": "https://avatars0.githubusercontent.com/u/9973046?v=4",
          "gravatar_id": "",
          "url": "https://api.github.com/users/riggaroo",
          "html_url": "https://github.com/riggaroo",
          "followers_url": "https://api.github.com/users/riggaroo/followers",
          "following_url": "https://api.github.com/users/riggaroo/following{/other_user}",
          "gists_url": "https://api.github.com/users/riggaroo/gists{/gist_id}",
          "starred_url": "https://api.github.com/users/riggaroo/starred{/owner}{/repo}",
          "subscriptions_url": "https://api.github.com/users/riggaroo/subscriptions",
          "organizations_url": "https://api.github.com/users/riggaroo/orgs",
          "repos_url": "https://api.github.com/users/riggaroo/repos",
          "events_url": "https://api.github.com/users/riggaroo/events{/privacy}",
          "received_events_url": "https://api.github.com/users/riggaroo/received_events",
          "type": "User",
          "site_admin": false
        },
        "content_type": "application/vnd.android.package-archive",
        "state": "uploaded",
        "size": 3688348,
        "download_count": 10,
        "created_at": "2016-01-03T16:51:38Z",
        "updated_at": "2016-01-03T16:52:17Z",
        "browser_download_url": "https://github.com/bookdash/bookdash-android-app/releases/download/v1.0.12/app-prod-release.apk"
      }
    ],
    "tarball_url": "https://api.github.com/repos/bookdash/bookdash-android-app/tarball/v1.0.12",
    "zipball_url": "https://api.github.com/repos/bookdash/bookdash-android-app/zipball/v1.0.12",
    "body": "Added ability to see downloaded books.\nAdded option to invite friends with Google Play Services Invites\nSharing of books added\nSome bug fixes.\n"
  },
  {
    "url": "https://api.github.com/repos/bookdash/bookdash-android-app/releases/2208008",
    "assets_url": "https://api.github.com/repos/bookdash/bookdash-android-app/releases/2208008/assets",
    "upload_url": "https://uploads.github.com/repos/bookdash/bookdash-android-app/releases/2208008/assets{?name,label}",
    "html_url": "https://github.com/bookdash/bookdash-android-app/releases/tag/v1.0.11",
    "id": 2208008,
    "node_id": "MDc6UmVsZWFzZTIyMDgwMDg=",
    "tag_name": "v1.0.11",
    "target_commitish": "master",
    "name": "Fixed issue with Downloads",
    "draft": false,
    "author": {
      "login": "riggaroo",
      "id": 9973046,
      "node_id": "MDQ6VXNlcjk5NzMwNDY=",
      "avatar_url": "https://avatars0.githubusercontent.com/u/9973046?v=4",
      "gravatar_id": "",
      "url": "https://api.github.com/users/riggaroo",
      "html_url": "https://github.com/riggaroo",
      "followers_url": "https://api.github.com/users/riggaroo/followers",
      "following_url": "https://api.github.com/users/riggaroo/following{/other_user}",
      "gists_url": "https://api.github.com/users/riggaroo/gists{/gist_id}",
      "starred_url": "https://api.github.com/users/riggaroo/starred{/owner}{/repo}",
      "subscriptions_url": "https://api.github.com/users/riggaroo/subscriptions",
      "organizations_url": "https://api.github.com/users/riggaroo/orgs",
      "repos_url": "https://api.github.com/users/riggaroo/repos",
      "events_url": "https://api.github.com/users/riggaroo/events{/privacy}",
      "received_events_url": "https://api.github.com/users/riggaroo/received_events",
      "type": "User",
      "site_admin": false
    },
    "prerelease": false,
    "created_at": "2015-11-30T18:22:22Z",
    "published_at": "2015-11-30T18:25:14Z",
    "assets": [
      {
        "url": "https://api.github.com/repos/bookdash/bookdash-android-app/releases/assets/1084782",
        "id": 1084782,
        "node_id": "MDEyOlJlbGVhc2VBc3NldDEwODQ3ODI=",
        "name": "app-prod-release.apk",
        "label": null,
        "uploader": {
          "login": "riggaroo",
          "id": 9973046,
          "node_id": "MDQ6VXNlcjk5NzMwNDY=",
          "avatar_url": "https://avatars0.githubusercontent.com/u/9973046?v=4",
          "gravatar_id": "",
          "url": "https://api.github.com/users/riggaroo",
          "html_url": "https://github.com/riggaroo",
          "followers_url": "https://api.github.com/users/riggaroo/followers",
          "following_url": "https://api.github.com/users/riggaroo/following{/other_user}",
          "gists_url": "https://api.github.com/users/riggaroo/gists{/gist_id}",
          "starred_url": "https://api.github.com/users/riggaroo/starred{/owner}{/repo}",
          "subscriptions_url": "https://api.github.com/users/riggaroo/subscriptions",
          "organizations_url": "https://api.github.com/users/riggaroo/orgs",
          "repos_url": "https://api.github.com/users/riggaroo/repos",
          "events_url": "https://api.github.com/users/riggaroo/events{/privacy}",
          "received_events_url": "https://api.github.com/users/riggaroo/received_events",
          "type": "User",
          "site_admin": false
        },
        "content_type": "application/vnd.android.package-archive",
        "state": "uploaded",
        "size": 3646539,
        "download_count": 13,
        "created_at": "2015-11-30T18:24:21Z",
        "updated_at": "2015-11-30T18:24:58Z",
        "browser_download_url": "https://github.com/bookdash/bookdash-android-app/releases/download/v1.0.11/app-prod-release.apk"
      }
    ],
    "tarball_url": "https://api.github.com/repos/bookdash/bookdash-android-app/tarball/v1.0.11",
    "zipball_url": "https://api.github.com/repos/bookdash/bookdash-android-app/zipball/v1.0.11",
    "body": "Download of books was causing issues if clicking the button twice. \nAlso up'ed the version of the parse library which fixes a couple of issues that I experienced.\nSome UI Tweaks.\n"
  },
  {
    "url": "https://api.github.com/repos/bookdash/bookdash-android-app/releases/2202357",
    "assets_url": "https://api.github.com/repos/bookdash/bookdash-android-app/releases/2202357/assets",
    "upload_url": "https://uploads.github.com/repos/bookdash/bookdash-android-app/releases/2202357/assets{?name,label}",
    "html_url": "https://github.com/bookdash/bookdash-android-app/releases/tag/v1.0.10",
    "id": 2202357,
    "node_id": "MDc6UmVsZWFzZTIyMDIzNTc=",
    "tag_name": "v1.0.10",
    "target_commitish": "master",
    "name": "Release 1.0.10",
    "draft": false,
    "author": {
      "login": "riggaroo",
      "id": 9973046,
      "node_id": "MDQ6VXNlcjk5NzMwNDY=",
      "avatar_url": "https://avatars0.githubusercontent.com/u/9973046?v=4",
      "gravatar_id": "",
      "url": "https://api.github.com/users/riggaroo",
      "html_url": "https://github.com/riggaroo",
      "followers_url": "https://api.github.com/users/riggaroo/followers",
      "following_url": "https://api.github.com/users/riggaroo/following{/other_user}",
      "gists_url": "https://api.github.com/users/riggaroo/gists{/gist_id}",
      "starred_url": "https://api.github.com/users/riggaroo/starred{/owner}{/repo}",
      "subscriptions_url": "https://api.github.com/users/riggaroo/subscriptions",
      "organizations_url": "https://api.github.com/users/riggaroo/orgs",
      "repos_url": "https://api.github.com/users/riggaroo/repos",
      "events_url": "https://api.github.com/users/riggaroo/events{/privacy}",
      "received_events_url": "https://api.github.com/users/riggaroo/received_events",
      "type": "User",
      "site_admin": false
    },
    "prerelease": false,
    "created_at": "2015-11-29T13:43:58Z",
    "published_at": "2015-11-29T13:47:19Z",
    "assets": [
      {
        "url": "https://api.github.com/repos/bookdash/bookdash-android-app/releases/assets/1081564",
        "id": 1081564,
        "node_id": "MDEyOlJlbGVhc2VBc3NldDEwODE1NjQ=",
        "name": "app-prod-release.apk",
        "label": null,
        "uploader": {
          "login": "riggaroo",
          "id": 9973046,
          "node_id": "MDQ6VXNlcjk5NzMwNDY=",
          "avatar_url": "https://avatars0.githubusercontent.com/u/9973046?v=4",
          "gravatar_id": "",
          "url": "https://api.github.com/users/riggaroo",
          "html_url": "https://github.com/riggaroo",
          "followers_url": "https://api.github.com/users/riggaroo/followers",
          "following_url": "https://api.github.com/users/riggaroo/following{/other_user}",
          "gists_url": "https://api.github.com/users/riggaroo/gists{/gist_id}",
          "starred_url": "https://api.github.com/users/riggaroo/starred{/owner}{/repo}",
          "subscriptions_url": "https://api.github.com/users/riggaroo/subscriptions",
          "organizations_url": "https://api.github.com/users/riggaroo/orgs",
          "repos_url": "https://api.github.com/users/riggaroo/repos",
          "events_url": "https://api.github.com/users/riggaroo/events{/privacy}",
          "received_events_url": "https://api.github.com/users/riggaroo/received_events",
          "type": "User",
          "site_admin": false
        },
        "content_type": "application/vnd.android.package-archive",
        "state": "uploaded",
        "size": 3712154,
        "download_count": 18,
        "created_at": "2015-11-29T13:45:37Z",
        "updated_at": "2015-11-29T13:46:13Z",
        "browser_download_url": "https://github.com/bookdash/bookdash-android-app/releases/download/v1.0.10/app-prod-release.apk"
      }
    ],
    "tarball_url": "https://api.github.com/repos/bookdash/bookdash-android-app/tarball/v1.0.10",
    "zipball_url": "https://api.github.com/repos/bookdash/bookdash-android-app/zipball/v1.0.10",
    "body": "- Moved Language choice into toolbar selection\n- Improved book reading screen\n- Minor UI fixes\n"
  },
  {
    "url": "https://api.github.com/repos/bookdash/bookdash-android-app/releases/2192608",
    "assets_url": "https://api.github.com/repos/bookdash/bookdash-android-app/releases/2192608/assets",
    "upload_url": "https://uploads.github.com/repos/bookdash/bookdash-android-app/releases/2192608/assets{?name,label}",
    "html_url": "https://github.com/bookdash/bookdash-android-app/releases/tag/v1.0.9",
    "id": 2192608,
    "node_id": "MDc6UmVsZWFzZTIxOTI2MDg=",
    "tag_name": "v1.0.9",
    "target_commitish": "master",
    "name": "Release 1.0.9",
    "draft": false,
    "author": {
      "login": "riggaroo",
      "id": 9973046,
      "node_id": "MDQ6VXNlcjk5NzMwNDY=",
      "avatar_url": "https://avatars0.githubusercontent.com/u/9973046?v=4",
      "gravatar_id": "",
      "url": "https://api.github.com/users/riggaroo",
      "html_url": "https://github.com/riggaroo",
      "followers_url": "https://api.github.com/users/riggaroo/followers",
      "following_url": "https://api.github.com/users/riggaroo/following{/other_user}",
      "gists_url": "https://api.github.com/users/riggaroo/gists{/gist_id}",
      "starred_url": "https://api.github.com/users/riggaroo/starred{/owner}{/repo}",
      "subscriptions_url": "https://api.github.com/users/riggaroo/subscriptions",
      "organizations_url": "https://api.github.com/users/riggaroo/orgs",
      "repos_url": "https://api.github.com/users/riggaroo/repos",
      "events_url": "https://api.github.com/users/riggaroo/events{/privacy}",
      "received_events_url": "https://api.github.com/users/riggaroo/received_events",
      "type": "User",
      "site_admin": false
    },
    "prerelease": false,
    "created_at": "2015-11-26T16:51:50Z",
    "published_at": "2015-11-26T18:14:28Z",
    "assets": [
      {
        "url": "https://api.github.com/repos/bookdash/bookdash-android-app/releases/assets/1074375",
        "id": 1074375,
        "node_id": "MDEyOlJlbGVhc2VBc3NldDEwNzQzNzU=",
        "name": "app-prod-release.apk",
        "label": null,
        "uploader": {
          "login": "riggaroo",
          "id": 9973046,
          "node_id": "MDQ6VXNlcjk5NzMwNDY=",
          "avatar_url": "https://avatars0.githubusercontent.com/u/9973046?v=4",
          "gravatar_id": "",
          "url": "https://api.github.com/users/riggaroo",
          "html_url": "https://github.com/riggaroo",
          "followers_url": "https://api.github.com/users/riggaroo/followers",
          "following_url": "https://api.github.com/users/riggaroo/following{/other_user}",
          "gists_url": "https://api.github.com/users/riggaroo/gists{/gist_id}",
          "starred_url": "https://api.github.com/users/riggaroo/starred{/owner}{/repo}",
          "subscriptions_url": "https://api.github.com/users/riggaroo/subscriptions",
          "organizations_url": "https://api.github.com/users/riggaroo/orgs",
          "repos_url": "https://api.github.com/users/riggaroo/repos",
          "events_url": "https://api.github.com/users/riggaroo/events{/privacy}",
          "received_events_url": "https://api.github.com/users/riggaroo/received_events",
          "type": "User",
          "site_admin": false
        },
        "content_type": "application/vnd.android.package-archive",
        "state": "uploaded",
        "size": 3690244,
        "download_count": 17,
        "created_at": "2015-11-26T17:58:57Z",
        "updated_at": "2015-11-26T17:59:32Z",
        "browser_download_url": "https://github.com/bookdash/bookdash-android-app/releases/download/v1.0.9/app-prod-release.apk"
      }
    ],
    "tarball_url": "https://api.github.com/repos/bookdash/bookdash-android-app/tarball/v1.0.9",
    "zipball_url": "https://api.github.com/repos/bookdash/bookdash-android-app/zipball/v1.0.9",
    "body": "Initial Release of the book dash android application.\n"
  }
]
