[
  {
    "url": "https://api.github.com/repos/GEANT/CAT-Android/releases/21022979",
    "assets_url": "https://api.github.com/repos/GEANT/CAT-Android/releases/21022979/assets",
    "upload_url": "https://uploads.github.com/repos/GEANT/CAT-Android/releases/21022979/assets{?name,label}",
    "html_url": "https://github.com/GEANT/CAT-Android/releases/tag/1.2.14",
    "id": 21022979,
    "node_id": "MDc6UmVsZWFzZTIxMDIyOTc5",
    "tag_name": "1.2.14",
    "target_commitish": "master",
    "name": "Latest release with fix to manual search bug",
    "draft": false,
    "author": {
      "login": "GarethAyres",
      "id": 329527,
      "node_id": "MDQ6VXNlcjMyOTUyNw==",
      "avatar_url": "https://avatars1.githubusercontent.com/u/329527?v=4",
      "gravatar_id": "",
      "url": "https://api.github.com/users/GarethAyres",
      "html_url": "https://github.com/GarethAyres",
      "followers_url": "https://api.github.com/users/GarethAyres/followers",
      "following_url": "https://api.github.com/users/GarethAyres/following{/other_user}",
      "gists_url": "https://api.github.com/users/GarethAyres/gists{/gist_id}",
      "starred_url": "https://api.github.com/users/GarethAyres/starred{/owner}{/repo}",
      "subscriptions_url": "https://api.github.com/users/GarethAyres/subscriptions",
      "organizations_url": "https://api.github.com/users/GarethAyres/orgs",
      "repos_url": "https://api.github.com/users/GarethAyres/repos",
      "events_url": "https://api.github.com/users/GarethAyres/events{/privacy}",
      "received_events_url": "https://api.github.com/users/GarethAyres/received_events",
      "type": "User",
      "site_admin": false
    },
    "prerelease": false,
    "created_at": "2019-10-25T14:32:27Z",
    "published_at": "2019-10-28T13:50:25Z",
    "assets": [
      {
        "url": "https://api.github.com/repos/GEANT/CAT-Android/releases/assets/15781519",
        "id": 15781519,
        "node_id": "MDEyOlJlbGVhc2VBc3NldDE1NzgxNTE5",
        "name": "CAT-Android2-release.apk",
        "label": null,
        "uploader": {
          "login": "GarethAyres",
          "id": 329527,
          "node_id": "MDQ6VXNlcjMyOTUyNw==",
          "avatar_url": "https://avatars1.githubusercontent.com/u/329527?v=4",
          "gravatar_id": "",
          "url": "https://api.github.com/users/GarethAyres",
          "html_url": "https://github.com/GarethAyres",
          "followers_url": "https://api.github.com/users/GarethAyres/followers",
          "following_url": "https://api.github.com/users/GarethAyres/following{/other_user}",
          "gists_url": "https://api.github.com/users/GarethAyres/gists{/gist_id}",
          "starred_url": "https://api.github.com/users/GarethAyres/starred{/owner}{/repo}",
          "subscriptions_url": "https://api.github.com/users/GarethAyres/subscriptions",
          "organizations_url": "https://api.github.com/users/GarethAyres/orgs",
          "repos_url": "https://api.github.com/users/GarethAyres/repos",
          "events_url": "https://api.github.com/users/GarethAyres/events{/privacy}",
          "received_events_url": "https://api.github.com/users/GarethAyres/received_events",
          "type": "User",
          "site_admin": false
        },
        "content_type": "application/vnd.android.package-archive",
        "state": "uploaded",
        "size": 737889,
        "download_count": 26,
        "created_at": "2019-10-28T13:42:09Z",
        "updated_at": "2019-10-28T13:42:12Z",
        "browser_download_url": "https://github.com/GEANT/CAT-Android/releases/download/1.2.14/CAT-Android2-release.apk"
      }
    ],
    "tarball_url": "https://api.github.com/repos/GEANT/CAT-Android/tarball/1.2.14",
    "zipball_url": "https://api.github.com/repos/GEANT/CAT-Android/zipball/1.2.14",
    "body": "Release with Managed IdP Support\r\n\r\nwith fix for manual search bug fix from issue 39"
  },
  {
    "url": "https://api.github.com/repos/GEANT/CAT-Android/releases/15211843",
    "assets_url": "https://api.github.com/repos/GEANT/CAT-Android/releases/15211843/assets",
    "upload_url": "https://uploads.github.com/repos/GEANT/CAT-Android/releases/15211843/assets{?name,label}",
    "html_url": "https://github.com/GEANT/CAT-Android/releases/tag/1.2.12",
    "id": 15211843,
    "node_id": "MDc6UmVsZWFzZTE1MjExODQz",
    "tag_name": "1.2.12",
    "target_commitish": "master",
    "name": "Release with Managed IdP Support and fixes",
    "draft": false,
    "author": {
      "login": "GarethAyres",
      "id": 329527,
      "node_id": "MDQ6VXNlcjMyOTUyNw==",
      "avatar_url": "https://avatars1.githubusercontent.com/u/329527?v=4",
      "gravatar_id": "",
      "url": "https://api.github.com/users/GarethAyres",
      "html_url": "https://github.com/GarethAyres",
      "followers_url": "https://api.github.com/users/GarethAyres/followers",
      "following_url": "https://api.github.com/users/GarethAyres/following{/other_user}",
      "gists_url": "https://api.github.com/users/GarethAyres/gists{/gist_id}",
      "starred_url": "https://api.github.com/users/GarethAyres/starred{/owner}{/repo}",
      "subscriptions_url": "https://api.github.com/users/GarethAyres/subscriptions",
      "organizations_url": "https://api.github.com/users/GarethAyres/orgs",
      "repos_url": "https://api.github.com/users/GarethAyres/repos",
      "events_url": "https://api.github.com/users/GarethAyres/events{/privacy}",
      "received_events_url": "https://api.github.com/users/GarethAyres/received_events",
      "type": "User",
      "site_admin": false
    },
    "prerelease": false,
    "created_at": "2019-01-17T13:30:18Z",
    "published_at": "2019-01-28T10:33:01Z",
    "assets": [
      {
        "url": "https://api.github.com/repos/GEANT/CAT-Android/releases/assets/10812575",
        "id": 10812575,
        "node_id": "MDEyOlJlbGVhc2VBc3NldDEwODEyNTc1",
        "name": "CAT-Android2-release.apk",
        "label": null,
        "uploader": {
          "login": "GarethAyres",
          "id": 329527,
          "node_id": "MDQ6VXNlcjMyOTUyNw==",
          "avatar_url": "https://avatars1.githubusercontent.com/u/329527?v=4",
          "gravatar_id": "",
          "url": "https://api.github.com/users/GarethAyres",
          "html_url": "https://github.com/GarethAyres",
          "followers_url": "https://api.github.com/users/GarethAyres/followers",
          "following_url": "https://api.github.com/users/GarethAyres/following{/other_user}",
          "gists_url": "https://api.github.com/users/GarethAyres/gists{/gist_id}",
          "starred_url": "https://api.github.com/users/GarethAyres/starred{/owner}{/repo}",
          "subscriptions_url": "https://api.github.com/users/GarethAyres/subscriptions",
          "organizations_url": "https://api.github.com/users/GarethAyres/orgs",
          "repos_url": "https://api.github.com/users/GarethAyres/repos",
          "events_url": "https://api.github.com/users/GarethAyres/events{/privacy}",
          "received_events_url": "https://api.github.com/users/GarethAyres/received_events",
          "type": "User",
          "site_admin": false
        },
        "content_type": "application/vnd.android.package-archive",
        "state": "uploaded",
        "size": 727626,
        "download_count": 1756,
        "created_at": "2019-01-28T10:32:05Z",
        "updated_at": "2019-01-28T10:32:06Z",
        "browser_download_url": "https://github.com/GEANT/CAT-Android/releases/download/1.2.12/CAT-Android2-release.apk"
      }
    ],
    "tarball_url": "https://api.github.com/repos/GEANT/CAT-Android/tarball/1.2.12",
    "zipball_url": "https://api.github.com/repos/GEANT/CAT-Android/zipball/1.2.12",
    "body": "Release with Managed IdP Support\r\n\r\nThis is the second release with Managed IdP support, and includes some fixes identified from previous release and TLS support. \r\nTLS with PIN using eap-config files from hosted managed idp eduroam cat website.\r\nThis release is the first to move to the new request permissions methodology, where runtime checks for permissions are required.\r\nChanged target SDK to 26\r\nAlso has some bug fixes to profile discovery process."
  },
  {
    "url": "https://api.github.com/repos/GEANT/CAT-Android/releases/14159705",
    "assets_url": "https://api.github.com/repos/GEANT/CAT-Android/releases/14159705/assets",
    "upload_url": "https://uploads.github.com/repos/GEANT/CAT-Android/releases/14159705/assets{?name,label}",
    "html_url": "https://github.com/GEANT/CAT-Android/releases/tag/1.2.8",
    "id": 14159705,
    "node_id": "MDc6UmVsZWFzZTE0MTU5NzA1",
    "tag_name": "1.2.8",
    "target_commitish": "master",
    "name": "Release with Managed IdP Support (production)",
    "draft": false,
    "author": {
      "login": "GarethAyres",
      "id": 329527,
      "node_id": "MDQ6VXNlcjMyOTUyNw==",
      "avatar_url": "https://avatars1.githubusercontent.com/u/329527?v=4",
      "gravatar_id": "",
      "url": "https://api.github.com/users/GarethAyres",
      "html_url": "https://github.com/GarethAyres",
      "followers_url": "https://api.github.com/users/GarethAyres/followers",
      "following_url": "https://api.github.com/users/GarethAyres/following{/other_user}",
      "gists_url": "https://api.github.com/users/GarethAyres/gists{/gist_id}",
      "starred_url": "https://api.github.com/users/GarethAyres/starred{/owner}{/repo}",
      "subscriptions_url": "https://api.github.com/users/GarethAyres/subscriptions",
      "organizations_url": "https://api.github.com/users/GarethAyres/orgs",
      "repos_url": "https://api.github.com/users/GarethAyres/repos",
      "events_url": "https://api.github.com/users/GarethAyres/events{/privacy}",
      "received_events_url": "https://api.github.com/users/GarethAyres/received_events",
      "type": "User",
      "site_admin": false
    },
    "prerelease": false,
    "created_at": "2018-11-23T16:03:58Z",
    "published_at": "2018-11-23T16:16:32Z",
    "assets": [
      {
        "url": "https://api.github.com/repos/GEANT/CAT-Android/releases/assets/9829737",
        "id": 9829737,
        "node_id": "MDEyOlJlbGVhc2VBc3NldDk4Mjk3Mzc=",
        "name": "CAT-Android2-release-v1-2-8.apk",
        "label": null,
        "uploader": {
          "login": "GarethAyres",
          "id": 329527,
          "node_id": "MDQ6VXNlcjMyOTUyNw==",
          "avatar_url": "https://avatars1.githubusercontent.com/u/329527?v=4",
          "gravatar_id": "",
          "url": "https://api.github.com/users/GarethAyres",
          "html_url": "https://github.com/GarethAyres",
          "followers_url": "https://api.github.com/users/GarethAyres/followers",
          "following_url": "https://api.github.com/users/GarethAyres/following{/other_user}",
          "gists_url": "https://api.github.com/users/GarethAyres/gists{/gist_id}",
          "starred_url": "https://api.github.com/users/GarethAyres/starred{/owner}{/repo}",
          "subscriptions_url": "https://api.github.com/users/GarethAyres/subscriptions",
          "organizations_url": "https://api.github.com/users/GarethAyres/orgs",
          "repos_url": "https://api.github.com/users/GarethAyres/repos",
          "events_url": "https://api.github.com/users/GarethAyres/events{/privacy}",
          "received_events_url": "https://api.github.com/users/GarethAyres/received_events",
          "type": "User",
          "site_admin": false
        },
        "content_type": "application/vnd.android.package-archive",
        "state": "uploaded",
        "size": 727426,
        "download_count": 8,
        "created_at": "2018-11-23T16:15:59Z",
        "updated_at": "2018-11-23T16:16:32Z",
        "browser_download_url": "https://github.com/GEANT/CAT-Android/releases/download/1.2.8/CAT-Android2-release-v1-2-8.apk"
      }
    ],
    "tarball_url": "https://api.github.com/repos/GEANT/CAT-Android/tarball/1.2.8",
    "zipball_url": "https://api.github.com/repos/GEANT/CAT-Android/zipball/1.2.8",
    "body": "Release with Managed IdP Support\r\n\r\nThis is the first release moving to productions with Managed IdP support.\r\nTLS with PIN using eap-config files from hosted managed idp eduroam cat webaite.\r\nThis release is the first to move to the new request permissions methodology, where runtime checks for permissions are required.\r\nChanged target SDK to 26\r\nAlso has some bug fixes to profile discovery process."
  },
  {
    "url": "https://api.github.com/repos/GEANT/CAT-Android/releases/13972764",
    "assets_url": "https://api.github.com/repos/GEANT/CAT-Android/releases/13972764/assets",
    "upload_url": "https://uploads.github.com/repos/GEANT/CAT-Android/releases/13972764/assets{?name,label}",
    "html_url": "https://github.com/GEANT/CAT-Android/releases/tag/v1.2.7",
    "id": 13972764,
    "node_id": "MDc6UmVsZWFzZTEzOTcyNzY0",
    "tag_name": "v1.2.7",
    "target_commitish": "master",
    "name": "Release with Managed IdP Support",
    "draft": false,
    "author": {
      "login": "GarethAyres",
      "id": 329527,
      "node_id": "MDQ6VXNlcjMyOTUyNw==",
      "avatar_url": "https://avatars1.githubusercontent.com/u/329527?v=4",
      "gravatar_id": "",
      "url": "https://api.github.com/users/GarethAyres",
      "html_url": "https://github.com/GarethAyres",
      "followers_url": "https://api.github.com/users/GarethAyres/followers",
      "following_url": "https://api.github.com/users/GarethAyres/following{/other_user}",
      "gists_url": "https://api.github.com/users/GarethAyres/gists{/gist_id}",
      "starred_url": "https://api.github.com/users/GarethAyres/starred{/owner}{/repo}",
      "subscriptions_url": "https://api.github.com/users/GarethAyres/subscriptions",
      "organizations_url": "https://api.github.com/users/GarethAyres/orgs",
      "repos_url": "https://api.github.com/users/GarethAyres/repos",
      "events_url": "https://api.github.com/users/GarethAyres/events{/privacy}",
      "received_events_url": "https://api.github.com/users/GarethAyres/received_events",
      "type": "User",
      "site_admin": false
    },
    "prerelease": false,
    "created_at": "2018-11-13T08:33:25Z",
    "published_at": "2018-11-13T11:48:06Z",
    "assets": [

    ],
    "tarball_url": "https://api.github.com/repos/GEANT/CAT-Android/tarball/v1.2.7",
    "zipball_url": "https://api.github.com/repos/GEANT/CAT-Android/zipball/v1.2.7",
    "body": "This is the first release moving from beta with Managed IdP support.\r\nTLS with PIN using eap-config files from hosted managed idp eduroam cat webaite.\r\nThis release is the first to move to the new request permissions methodology, where runtime checks for permissions are required. \r\nAlso has some bug fixes to profile discovery process."
  }
]
