[
  {
    "url": "https://api.github.com/repos/gitpoint/git-point/releases/17490457",
    "assets_url": "https://api.github.com/repos/gitpoint/git-point/releases/17490457/assets",
    "upload_url": "https://uploads.github.com/repos/gitpoint/git-point/releases/17490457/assets{?name,label}",
    "html_url": "https://github.com/gitpoint/git-point/releases/tag/1.7.1",
    "id": 17490457,
    "node_id": "MDc6UmVsZWFzZTE3NDkwNDU3",
    "tag_name": "1.7.1",
    "target_commitish": "master",
    "name": "Version 1.7.1",
    "draft": false,
    "author": {
      "login": "chinesedfan",
      "id": 1736154,
      "node_id": "MDQ6VXNlcjE3MzYxNTQ=",
      "avatar_url": "https://avatars3.githubusercontent.com/u/1736154?v=4",
      "gravatar_id": "",
      "url": "https://api.github.com/users/chinesedfan",
      "html_url": "https://github.com/chinesedfan",
      "followers_url": "https://api.github.com/users/chinesedfan/followers",
      "following_url": "https://api.github.com/users/chinesedfan/following{/other_user}",
      "gists_url": "https://api.github.com/users/chinesedfan/gists{/gist_id}",
      "starred_url": "https://api.github.com/users/chinesedfan/starred{/owner}{/repo}",
      "subscriptions_url": "https://api.github.com/users/chinesedfan/subscriptions",
      "organizations_url": "https://api.github.com/users/chinesedfan/orgs",
      "repos_url": "https://api.github.com/users/chinesedfan/repos",
      "events_url": "https://api.github.com/users/chinesedfan/events{/privacy}",
      "received_events_url": "https://api.github.com/users/chinesedfan/received_events",
      "type": "User",
      "site_admin": false
    },
    "prerelease": false,
    "created_at": "2019-05-21T14:28:17Z",
    "published_at": "2019-05-21T14:33:58Z",
    "assets": [
      {
        "url": "https://api.github.com/repos/gitpoint/git-point/releases/assets/12835935",
        "id": 12835935,
        "node_id": "MDEyOlJlbGVhc2VBc3NldDEyODM1OTM1",
        "name": "GitPoint.apk",
        "label": null,
        "uploader": {
          "login": "chinesedfan",
          "id": 1736154,
          "node_id": "MDQ6VXNlcjE3MzYxNTQ=",
          "avatar_url": "https://avatars3.githubusercontent.com/u/1736154?v=4",
          "gravatar_id": "",
          "url": "https://api.github.com/users/chinesedfan",
          "html_url": "https://github.com/chinesedfan",
          "followers_url": "https://api.github.com/users/chinesedfan/followers",
          "following_url": "https://api.github.com/users/chinesedfan/following{/other_user}",
          "gists_url": "https://api.github.com/users/chinesedfan/gists{/gist_id}",
          "starred_url": "https://api.github.com/users/chinesedfan/starred{/owner}{/repo}",
          "subscriptions_url": "https://api.github.com/users/chinesedfan/subscriptions",
          "organizations_url": "https://api.github.com/users/chinesedfan/orgs",
          "repos_url": "https://api.github.com/users/chinesedfan/repos",
          "events_url": "https://api.github.com/users/chinesedfan/events{/privacy}",
          "received_events_url": "https://api.github.com/users/chinesedfan/received_events",
          "type": "User",
          "site_admin": false
        },
        "content_type": "application/vnd.android.package-archive",
        "state": "uploaded",
        "size": 10421704,
        "download_count": 183,
        "created_at": "2019-05-23T15:58:17Z",
        "updated_at": "2019-05-23T15:58:34Z",
        "browser_download_url": "https://github.com/gitpoint/git-point/releases/download/1.7.1/GitPoint.apk"
      }
    ],
    "tarball_url": "https://api.github.com/repos/gitpoint/git-point/tarball/1.7.1",
    "zipball_url": "https://api.github.com/repos/gitpoint/git-point/zipball/1.7.1",
    "body": "Long time no release, friends.\r\n\r\n- Support pagination in more screens\r\n- Fix some crash bugs"
  },
  {
    "url": "https://api.github.com/repos/gitpoint/git-point/releases/14299867",
    "assets_url": "https://api.github.com/repos/gitpoint/git-point/releases/14299867/assets",
    "upload_url": "https://uploads.github.com/repos/gitpoint/git-point/releases/14299867/assets{?name,label}",
    "html_url": "https://github.com/gitpoint/git-point/releases/tag/1.7.0",
    "id": 14299867,
    "node_id": "MDc6UmVsZWFzZTE0Mjk5ODY3",
    "tag_name": "1.7.0",
    "target_commitish": "master",
    "name": "Version 1.7.0",
    "draft": false,
    "author": {
      "login": "housseindjirdeh",
      "id": 12476932,
      "node_id": "MDQ6VXNlcjEyNDc2OTMy",
      "avatar_url": "https://avatars3.githubusercontent.com/u/12476932?v=4",
      "gravatar_id": "",
      "url": "https://api.github.com/users/housseindjirdeh",
      "html_url": "https://github.com/housseindjirdeh",
      "followers_url": "https://api.github.com/users/housseindjirdeh/followers",
      "following_url": "https://api.github.com/users/housseindjirdeh/following{/other_user}",
      "gists_url": "https://api.github.com/users/housseindjirdeh/gists{/gist_id}",
      "starred_url": "https://api.github.com/users/housseindjirdeh/starred{/owner}{/repo}",
      "subscriptions_url": "https://api.github.com/users/housseindjirdeh/subscriptions",
      "organizations_url": "https://api.github.com/users/housseindjirdeh/orgs",
      "repos_url": "https://api.github.com/users/housseindjirdeh/repos",
      "events_url": "https://api.github.com/users/housseindjirdeh/events{/privacy}",
      "received_events_url": "https://api.github.com/users/housseindjirdeh/received_events",
      "type": "User",
      "site_admin": false
    },
    "prerelease": false,
    "created_at": "2018-12-01T03:41:18Z",
    "published_at": "2018-12-02T03:57:23Z",
    "assets": [

    ],
    "tarball_url": "https://api.github.com/repos/gitpoint/git-point/tarball/1.7.0",
    "zipball_url": "https://api.github.com/repos/gitpoint/git-point/zipball/1.7.0",
    "body": "Not an intended release. Please ignore."
  },
  {
    "url": "https://api.github.com/repos/gitpoint/git-point/releases/9701876",
    "assets_url": "https://api.github.com/repos/gitpoint/git-point/releases/9701876/assets",
    "upload_url": "https://uploads.github.com/repos/gitpoint/git-point/releases/9701876/assets{?name,label}",
    "html_url": "https://github.com/gitpoint/git-point/releases/tag/1.5.0",
    "id": 9701876,
    "node_id": "MDc6UmVsZWFzZTk3MDE4NzY=",
    "tag_name": "1.5.0",
    "target_commitish": "master",
    "name": "Version 1.5.0",
    "draft": false,
    "author": {
      "login": "housseindjirdeh",
      "id": 12476932,
      "node_id": "MDQ6VXNlcjEyNDc2OTMy",
      "avatar_url": "https://avatars3.githubusercontent.com/u/12476932?v=4",
      "gravatar_id": "",
      "url": "https://api.github.com/users/housseindjirdeh",
      "html_url": "https://github.com/housseindjirdeh",
      "followers_url": "https://api.github.com/users/housseindjirdeh/followers",
      "following_url": "https://api.github.com/users/housseindjirdeh/following{/other_user}",
      "gists_url": "https://api.github.com/users/housseindjirdeh/gists{/gist_id}",
      "starred_url": "https://api.github.com/users/housseindjirdeh/starred{/owner}{/repo}",
      "subscriptions_url": "https://api.github.com/users/housseindjirdeh/subscriptions",
      "organizations_url": "https://api.github.com/users/housseindjirdeh/orgs",
      "repos_url": "https://api.github.com/users/housseindjirdeh/repos",
      "events_url": "https://api.github.com/users/housseindjirdeh/events{/privacy}",
      "received_events_url": "https://api.github.com/users/housseindjirdeh/received_events",
      "type": "User",
      "site_admin": false
    },
    "prerelease": false,
    "created_at": "2018-02-16T03:08:10Z",
    "published_at": "2018-02-16T04:03:09Z",
    "assets": [
      {
        "url": "https://api.github.com/repos/gitpoint/git-point/releases/assets/6229445",
        "id": 6229445,
        "node_id": "MDEyOlJlbGVhc2VBc3NldDYyMjk0NDU=",
        "name": "GitPoint.apk",
        "label": null,
        "uploader": {
          "login": "housseindjirdeh",
          "id": 12476932,
          "node_id": "MDQ6VXNlcjEyNDc2OTMy",
          "avatar_url": "https://avatars3.githubusercontent.com/u/12476932?v=4",
          "gravatar_id": "",
          "url": "https://api.github.com/users/housseindjirdeh",
          "html_url": "https://github.com/housseindjirdeh",
          "followers_url": "https://api.github.com/users/housseindjirdeh/followers",
          "following_url": "https://api.github.com/users/housseindjirdeh/following{/other_user}",
          "gists_url": "https://api.github.com/users/housseindjirdeh/gists{/gist_id}",
          "starred_url": "https://api.github.com/users/housseindjirdeh/starred{/owner}{/repo}",
          "subscriptions_url": "https://api.github.com/users/housseindjirdeh/subscriptions",
          "organizations_url": "https://api.github.com/users/housseindjirdeh/orgs",
          "repos_url": "https://api.github.com/users/housseindjirdeh/repos",
          "events_url": "https://api.github.com/users/housseindjirdeh/events{/privacy}",
          "received_events_url": "https://api.github.com/users/housseindjirdeh/received_events",
          "type": "User",
          "site_admin": false
        },
        "content_type": "application/vnd.android.package-archive",
        "state": "uploaded",
        "size": 9680887,
        "download_count": 118,
        "created_at": "2018-02-16T04:02:17Z",
        "updated_at": "2018-02-16T04:03:09Z",
        "browser_download_url": "https://github.com/gitpoint/git-point/releases/download/1.5.0/GitPoint.apk"
      },
      {
        "url": "https://api.github.com/repos/gitpoint/git-point/releases/assets/6229447",
        "id": 6229447,
        "node_id": "MDEyOlJlbGVhc2VBc3NldDYyMjk0NDc=",
        "name": "GitPoint.ipa",
        "label": null,
        "uploader": {
          "login": "housseindjirdeh",
          "id": 12476932,
          "node_id": "MDQ6VXNlcjEyNDc2OTMy",
          "avatar_url": "https://avatars3.githubusercontent.com/u/12476932?v=4",
          "gravatar_id": "",
          "url": "https://api.github.com/users/housseindjirdeh",
          "html_url": "https://github.com/housseindjirdeh",
          "followers_url": "https://api.github.com/users/housseindjirdeh/followers",
          "following_url": "https://api.github.com/users/housseindjirdeh/following{/other_user}",
          "gists_url": "https://api.github.com/users/housseindjirdeh/gists{/gist_id}",
          "starred_url": "https://api.github.com/users/housseindjirdeh/starred{/owner}{/repo}",
          "subscriptions_url": "https://api.github.com/users/housseindjirdeh/subscriptions",
          "organizations_url": "https://api.github.com/users/housseindjirdeh/orgs",
          "repos_url": "https://api.github.com/users/housseindjirdeh/repos",
          "events_url": "https://api.github.com/users/housseindjirdeh/events{/privacy}",
          "received_events_url": "https://api.github.com/users/housseindjirdeh/received_events",
          "type": "User",
          "site_admin": false
        },
        "content_type": "application/octet-stream",
        "state": "uploaded",
        "size": 12258660,
        "download_count": 21,
        "created_at": "2018-02-16T04:02:45Z",
        "updated_at": "2018-02-16T04:02:50Z",
        "browser_download_url": "https://github.com/gitpoint/git-point/releases/download/1.5.0/GitPoint.ipa"
      }
    ],
    "tarball_url": "https://api.github.com/repos/gitpoint/git-point/tarball/1.5.0",
    "zipball_url": "https://api.github.com/repos/gitpoint/git-point/zipball/1.5.0",
    "body": ""
  },
  {
    "url": "https://api.github.com/repos/gitpoint/git-point/releases/9289360",
    "assets_url": "https://api.github.com/repos/gitpoint/git-point/releases/9289360/assets",
    "upload_url": "https://uploads.github.com/repos/gitpoint/git-point/releases/9289360/assets{?name,label}",
    "html_url": "https://github.com/gitpoint/git-point/releases/tag/hotfix",
    "id": 9289360,
    "node_id": "MDc6UmVsZWFzZTkyODkzNjA=",
    "tag_name": "hotfix",
    "target_commitish": "master",
    "name": "Authorization Android Fix",
    "draft": false,
    "author": {
      "login": "housseindjirdeh",
      "id": 12476932,
      "node_id": "MDQ6VXNlcjEyNDc2OTMy",
      "avatar_url": "https://avatars3.githubusercontent.com/u/12476932?v=4",
      "gravatar_id": "",
      "url": "https://api.github.com/users/housseindjirdeh",
      "html_url": "https://github.com/housseindjirdeh",
      "followers_url": "https://api.github.com/users/housseindjirdeh/followers",
      "following_url": "https://api.github.com/users/housseindjirdeh/following{/other_user}",
      "gists_url": "https://api.github.com/users/housseindjirdeh/gists{/gist_id}",
      "starred_url": "https://api.github.com/users/housseindjirdeh/starred{/owner}{/repo}",
      "subscriptions_url": "https://api.github.com/users/housseindjirdeh/subscriptions",
      "organizations_url": "https://api.github.com/users/housseindjirdeh/orgs",
      "repos_url": "https://api.github.com/users/housseindjirdeh/repos",
      "events_url": "https://api.github.com/users/housseindjirdeh/events{/privacy}",
      "received_events_url": "https://api.github.com/users/housseindjirdeh/received_events",
      "type": "User",
      "site_admin": false
    },
    "prerelease": true,
    "created_at": "2018-01-17T16:56:30Z",
    "published_at": "2018-01-18T15:10:13Z",
    "assets": [
      {
        "url": "https://api.github.com/repos/gitpoint/git-point/releases/assets/5913424",
        "id": 5913424,
        "node_id": "MDEyOlJlbGVhc2VBc3NldDU5MTM0MjQ=",
        "name": "GitPoint.apk",
        "label": null,
        "uploader": {
          "login": "housseindjirdeh",
          "id": 12476932,
          "node_id": "MDQ6VXNlcjEyNDc2OTMy",
          "avatar_url": "https://avatars3.githubusercontent.com/u/12476932?v=4",
          "gravatar_id": "",
          "url": "https://api.github.com/users/housseindjirdeh",
          "html_url": "https://github.com/housseindjirdeh",
          "followers_url": "https://api.github.com/users/housseindjirdeh/followers",
          "following_url": "https://api.github.com/users/housseindjirdeh/following{/other_user}",
          "gists_url": "https://api.github.com/users/housseindjirdeh/gists{/gist_id}",
          "starred_url": "https://api.github.com/users/housseindjirdeh/starred{/owner}{/repo}",
          "subscriptions_url": "https://api.github.com/users/housseindjirdeh/subscriptions",
          "organizations_url": "https://api.github.com/users/housseindjirdeh/orgs",
          "repos_url": "https://api.github.com/users/housseindjirdeh/repos",
          "events_url": "https://api.github.com/users/housseindjirdeh/events{/privacy}",
          "received_events_url": "https://api.github.com/users/housseindjirdeh/received_events",
          "type": "User",
          "site_admin": false
        },
        "content_type": "application/vnd.android.package-archive",
        "state": "uploaded",
        "size": 9446913,
        "download_count": 35,
        "created_at": "2018-01-18T15:09:34Z",
        "updated_at": "2018-01-18T15:10:13Z",
        "browser_download_url": "https://github.com/gitpoint/git-point/releases/download/hotfix/GitPoint.apk"
      }
    ],
    "tarball_url": "https://api.github.com/repos/gitpoint/git-point/tarball/hotfix",
    "zipball_url": "https://api.github.com/repos/gitpoint/git-point/zipball/hotfix",
    "body": ""
  },
  {
    "url": "https://api.github.com/repos/gitpoint/git-point/releases/8955955",
    "assets_url": "https://api.github.com/repos/gitpoint/git-point/releases/8955955/assets",
    "upload_url": "https://uploads.github.com/repos/gitpoint/git-point/releases/8955955/assets{?name,label}",
    "html_url": "https://github.com/gitpoint/git-point/releases/tag/1.4.1",
    "id": 8955955,
    "node_id": "MDc6UmVsZWFzZTg5NTU5NTU=",
    "tag_name": "1.4.1",
    "target_commitish": "master",
    "name": "Version 1.4.1",
    "draft": false,
    "author": {
      "login": "housseindjirdeh",
      "id": 12476932,
      "node_id": "MDQ6VXNlcjEyNDc2OTMy",
      "avatar_url": "https://avatars3.githubusercontent.com/u/12476932?v=4",
      "gravatar_id": "",
      "url": "https://api.github.com/users/housseindjirdeh",
      "html_url": "https://github.com/housseindjirdeh",
      "followers_url": "https://api.github.com/users/housseindjirdeh/followers",
      "following_url": "https://api.github.com/users/housseindjirdeh/following{/other_user}",
      "gists_url": "https://api.github.com/users/housseindjirdeh/gists{/gist_id}",
      "starred_url": "https://api.github.com/users/housseindjirdeh/starred{/owner}{/repo}",
      "subscriptions_url": "https://api.github.com/users/housseindjirdeh/subscriptions",
      "organizations_url": "https://api.github.com/users/housseindjirdeh/orgs",
      "repos_url": "https://api.github.com/users/housseindjirdeh/repos",
      "events_url": "https://api.github.com/users/housseindjirdeh/events{/privacy}",
      "received_events_url": "https://api.github.com/users/housseindjirdeh/received_events",
      "type": "User",
      "site_admin": false
    },
    "prerelease": false,
    "created_at": "2017-12-15T12:21:29Z",
    "published_at": "2017-12-19T02:29:38Z",
    "assets": [
      {
        "url": "https://api.github.com/repos/gitpoint/git-point/releases/assets/5661489",
        "id": 5661489,
        "node_id": "MDEyOlJlbGVhc2VBc3NldDU2NjE0ODk=",
        "name": "GitPoint.apk",
        "label": null,
        "uploader": {
          "login": "housseindjirdeh",
          "id": 12476932,
          "node_id": "MDQ6VXNlcjEyNDc2OTMy",
          "avatar_url": "https://avatars3.githubusercontent.com/u/12476932?v=4",
          "gravatar_id": "",
          "url": "https://api.github.com/users/housseindjirdeh",
          "html_url": "https://github.com/housseindjirdeh",
          "followers_url": "https://api.github.com/users/housseindjirdeh/followers",
          "following_url": "https://api.github.com/users/housseindjirdeh/following{/other_user}",
          "gists_url": "https://api.github.com/users/housseindjirdeh/gists{/gist_id}",
          "starred_url": "https://api.github.com/users/housseindjirdeh/starred{/owner}{/repo}",
          "subscriptions_url": "https://api.github.com/users/housseindjirdeh/subscriptions",
          "organizations_url": "https://api.github.com/users/housseindjirdeh/orgs",
          "repos_url": "https://api.github.com/users/housseindjirdeh/repos",
          "events_url": "https://api.github.com/users/housseindjirdeh/events{/privacy}",
          "received_events_url": "https://api.github.com/users/housseindjirdeh/received_events",
          "type": "User",
          "site_admin": false
        },
        "content_type": "application/vnd.android.package-archive",
        "state": "uploaded",
        "size": 9453323,
        "download_count": 82,
        "created_at": "2017-12-19T02:27:59Z",
        "updated_at": "2017-12-19T02:29:38Z",
        "browser_download_url": "https://github.com/gitpoint/git-point/releases/download/1.4.1/GitPoint.apk"
      },
      {
        "url": "https://api.github.com/repos/gitpoint/git-point/releases/assets/5661500",
        "id": 5661500,
        "node_id": "MDEyOlJlbGVhc2VBc3NldDU2NjE1MDA=",
        "name": "GitPoint.ipa",
        "label": null,
        "uploader": {
          "login": "housseindjirdeh",
          "id": 12476932,
          "node_id": "MDQ6VXNlcjEyNDc2OTMy",
          "avatar_url": "https://avatars3.githubusercontent.com/u/12476932?v=4",
          "gravatar_id": "",
          "url": "https://api.github.com/users/housseindjirdeh",
          "html_url": "https://github.com/housseindjirdeh",
          "followers_url": "https://api.github.com/users/housseindjirdeh/followers",
          "following_url": "https://api.github.com/users/housseindjirdeh/following{/other_user}",
          "gists_url": "https://api.github.com/users/housseindjirdeh/gists{/gist_id}",
          "starred_url": "https://api.github.com/users/housseindjirdeh/starred{/owner}{/repo}",
          "subscriptions_url": "https://api.github.com/users/housseindjirdeh/subscriptions",
          "organizations_url": "https://api.github.com/users/housseindjirdeh/orgs",
          "repos_url": "https://api.github.com/users/housseindjirdeh/repos",
          "events_url": "https://api.github.com/users/housseindjirdeh/events{/privacy}",
          "received_events_url": "https://api.github.com/users/housseindjirdeh/received_events",
          "type": "User",
          "site_admin": false
        },
        "content_type": "application/octet-stream",
        "state": "uploaded",
        "size": 10918298,
        "download_count": 28,
        "created_at": "2017-12-19T02:29:24Z",
        "updated_at": "2017-12-19T02:29:36Z",
        "browser_download_url": "https://github.com/gitpoint/git-point/releases/download/1.4.1/GitPoint.ipa"
      }
    ],
    "tarball_url": "https://api.github.com/repos/gitpoint/git-point/tarball/1.4.1",
    "zipball_url": "https://api.github.com/repos/gitpoint/git-point/zipball/1.4.1",
    "body": "Fix to package.json's version number"
  },
  {
    "url": "https://api.github.com/repos/gitpoint/git-point/releases/8915945",
    "assets_url": "https://api.github.com/repos/gitpoint/git-point/releases/8915945/assets",
    "upload_url": "https://uploads.github.com/repos/gitpoint/git-point/releases/8915945/assets{?name,label}",
    "html_url": "https://github.com/gitpoint/git-point/releases/tag/1.4.0",
    "id": 8915945,
    "node_id": "MDc6UmVsZWFzZTg5MTU5NDU=",
    "tag_name": "1.4.0",
    "target_commitish": "master",
    "name": "Version 1.4.0",
    "draft": false,
    "author": {
      "login": "housseindjirdeh",
      "id": 12476932,
      "node_id": "MDQ6VXNlcjEyNDc2OTMy",
      "avatar_url": "https://avatars3.githubusercontent.com/u/12476932?v=4",
      "gravatar_id": "",
      "url": "https://api.github.com/users/housseindjirdeh",
      "html_url": "https://github.com/housseindjirdeh",
      "followers_url": "https://api.github.com/users/housseindjirdeh/followers",
      "following_url": "https://api.github.com/users/housseindjirdeh/following{/other_user}",
      "gists_url": "https://api.github.com/users/housseindjirdeh/gists{/gist_id}",
      "starred_url": "https://api.github.com/users/housseindjirdeh/starred{/owner}{/repo}",
      "subscriptions_url": "https://api.github.com/users/housseindjirdeh/subscriptions",
      "organizations_url": "https://api.github.com/users/housseindjirdeh/orgs",
      "repos_url": "https://api.github.com/users/housseindjirdeh/repos",
      "events_url": "https://api.github.com/users/housseindjirdeh/events{/privacy}",
      "received_events_url": "https://api.github.com/users/housseindjirdeh/received_events",
      "type": "User",
      "site_admin": false
    },
    "prerelease": false,
    "created_at": "2017-12-12T16:13:49Z",
    "published_at": "2017-12-15T01:59:45Z",
    "assets": [
      {
        "url": "https://api.github.com/repos/gitpoint/git-point/releases/assets/5628613",
        "id": 5628613,
        "node_id": "MDEyOlJlbGVhc2VBc3NldDU2Mjg2MTM=",
        "name": "GitPoint.apk",
        "label": null,
        "uploader": {
          "login": "housseindjirdeh",
          "id": 12476932,
          "node_id": "MDQ6VXNlcjEyNDc2OTMy",
          "avatar_url": "https://avatars3.githubusercontent.com/u/12476932?v=4",
          "gravatar_id": "",
          "url": "https://api.github.com/users/housseindjirdeh",
          "html_url": "https://github.com/housseindjirdeh",
          "followers_url": "https://api.github.com/users/housseindjirdeh/followers",
          "following_url": "https://api.github.com/users/housseindjirdeh/following{/other_user}",
          "gists_url": "https://api.github.com/users/housseindjirdeh/gists{/gist_id}",
          "starred_url": "https://api.github.com/users/housseindjirdeh/starred{/owner}{/repo}",
          "subscriptions_url": "https://api.github.com/users/housseindjirdeh/subscriptions",
          "organizations_url": "https://api.github.com/users/housseindjirdeh/orgs",
          "repos_url": "https://api.github.com/users/housseindjirdeh/repos",
          "events_url": "https://api.github.com/users/housseindjirdeh/events{/privacy}",
          "received_events_url": "https://api.github.com/users/housseindjirdeh/received_events",
          "type": "User",
          "site_admin": false
        },
        "content_type": "application/vnd.android.package-archive",
        "state": "uploaded",
        "size": 9984129,
        "download_count": 17,
        "created_at": "2017-12-15T01:52:46Z",
        "updated_at": "2017-12-15T01:59:45Z",
        "browser_download_url": "https://github.com/gitpoint/git-point/releases/download/1.4.0/GitPoint.apk"
      },
      {
        "url": "https://api.github.com/repos/gitpoint/git-point/releases/assets/5628672",
        "id": 5628672,
        "node_id": "MDEyOlJlbGVhc2VBc3NldDU2Mjg2NzI=",
        "name": "GitPoint.ipa",
        "label": null,
        "uploader": {
          "login": "housseindjirdeh",
          "id": 12476932,
          "node_id": "MDQ6VXNlcjEyNDc2OTMy",
          "avatar_url": "https://avatars3.githubusercontent.com/u/12476932?v=4",
          "gravatar_id": "",
          "url": "https://api.github.com/users/housseindjirdeh",
          "html_url": "https://github.com/housseindjirdeh",
          "followers_url": "https://api.github.com/users/housseindjirdeh/followers",
          "following_url": "https://api.github.com/users/housseindjirdeh/following{/other_user}",
          "gists_url": "https://api.github.com/users/housseindjirdeh/gists{/gist_id}",
          "starred_url": "https://api.github.com/users/housseindjirdeh/starred{/owner}{/repo}",
          "subscriptions_url": "https://api.github.com/users/housseindjirdeh/subscriptions",
          "organizations_url": "https://api.github.com/users/housseindjirdeh/orgs",
          "repos_url": "https://api.github.com/users/housseindjirdeh/repos",
          "events_url": "https://api.github.com/users/housseindjirdeh/events{/privacy}",
          "received_events_url": "https://api.github.com/users/housseindjirdeh/received_events",
          "type": "User",
          "site_admin": false
        },
        "content_type": "application/octet-stream",
        "state": "uploaded",
        "size": 10918302,
        "download_count": 9,
        "created_at": "2017-12-15T01:59:31Z",
        "updated_at": "2017-12-15T01:59:32Z",
        "browser_download_url": "https://github.com/gitpoint/git-point/releases/download/1.4.0/GitPoint.ipa"
      }
    ],
    "tarball_url": "https://api.github.com/repos/gitpoint/git-point/tarball/1.4.0",
    "zipball_url": "https://api.github.com/repos/gitpoint/git-point/zipball/1.4.0",
    "body": "More languages added, open in browser support and bugfixes."
  },
  {
    "url": "https://api.github.com/repos/gitpoint/git-point/releases/7996030",
    "assets_url": "https://api.github.com/repos/gitpoint/git-point/releases/7996030/assets",
    "upload_url": "https://uploads.github.com/repos/gitpoint/git-point/releases/7996030/assets{?name,label}",
    "html_url": "https://github.com/gitpoint/git-point/releases/tag/1.3.1",
    "id": 7996030,
    "node_id": "MDc6UmVsZWFzZTc5OTYwMzA=",
    "tag_name": "1.3.1",
    "target_commitish": "master",
    "name": "Version 1.3.1",
    "draft": false,
    "author": {
      "login": "housseindjirdeh",
      "id": 12476932,
      "node_id": "MDQ6VXNlcjEyNDc2OTMy",
      "avatar_url": "https://avatars3.githubusercontent.com/u/12476932?v=4",
      "gravatar_id": "",
      "url": "https://api.github.com/users/housseindjirdeh",
      "html_url": "https://github.com/housseindjirdeh",
      "followers_url": "https://api.github.com/users/housseindjirdeh/followers",
      "following_url": "https://api.github.com/users/housseindjirdeh/following{/other_user}",
      "gists_url": "https://api.github.com/users/housseindjirdeh/gists{/gist_id}",
      "starred_url": "https://api.github.com/users/housseindjirdeh/starred{/owner}{/repo}",
      "subscriptions_url": "https://api.github.com/users/housseindjirdeh/subscriptions",
      "organizations_url": "https://api.github.com/users/housseindjirdeh/orgs",
      "repos_url": "https://api.github.com/users/housseindjirdeh/repos",
      "events_url": "https://api.github.com/users/housseindjirdeh/events{/privacy}",
      "received_events_url": "https://api.github.com/users/housseindjirdeh/received_events",
      "type": "User",
      "site_admin": false
    },
    "prerelease": false,
    "created_at": "2017-10-04T15:10:38Z",
    "published_at": "2017-10-04T15:37:39Z",
    "assets": [
      {
        "url": "https://api.github.com/repos/gitpoint/git-point/releases/assets/4982611",
        "id": 4982611,
        "node_id": "MDEyOlJlbGVhc2VBc3NldDQ5ODI2MTE=",
        "name": "GitPoint.apk",
        "label": null,
        "uploader": {
          "login": "housseindjirdeh",
          "id": 12476932,
          "node_id": "MDQ6VXNlcjEyNDc2OTMy",
          "avatar_url": "https://avatars3.githubusercontent.com/u/12476932?v=4",
          "gravatar_id": "",
          "url": "https://api.github.com/users/housseindjirdeh",
          "html_url": "https://github.com/housseindjirdeh",
          "followers_url": "https://api.github.com/users/housseindjirdeh/followers",
          "following_url": "https://api.github.com/users/housseindjirdeh/following{/other_user}",
          "gists_url": "https://api.github.com/users/housseindjirdeh/gists{/gist_id}",
          "starred_url": "https://api.github.com/users/housseindjirdeh/starred{/owner}{/repo}",
          "subscriptions_url": "https://api.github.com/users/housseindjirdeh/subscriptions",
          "organizations_url": "https://api.github.com/users/housseindjirdeh/orgs",
          "repos_url": "https://api.github.com/users/housseindjirdeh/repos",
          "events_url": "https://api.github.com/users/housseindjirdeh/events{/privacy}",
          "received_events_url": "https://api.github.com/users/housseindjirdeh/received_events",
          "type": "User",
          "site_admin": false
        },
        "content_type": "application/vnd.android.package-archive",
        "state": "uploaded",
        "size": 9777430,
        "download_count": 38,
        "created_at": "2017-10-04T15:37:31Z",
        "updated_at": "2017-10-04T15:37:39Z",
        "browser_download_url": "https://github.com/gitpoint/git-point/releases/download/1.3.1/GitPoint.apk"
      }
    ],
    "tarball_url": "https://api.github.com/repos/gitpoint/git-point/tarball/1.3.1",
    "zipball_url": "https://api.github.com/repos/gitpoint/git-point/zipball/1.3.1",
    "body": "Minor bug fixes:\r\n\r\n- Fix README rendering for Android\r\n- Fix TextInput height on mount on edit issue comment screen for Android"
  },
  {
    "url": "https://api.github.com/repos/gitpoint/git-point/releases/7987839",
    "assets_url": "https://api.github.com/repos/gitpoint/git-point/releases/7987839/assets",
    "upload_url": "https://uploads.github.com/repos/gitpoint/git-point/releases/7987839/assets{?name,label}",
    "html_url": "https://github.com/gitpoint/git-point/releases/tag/1.3.0",
    "id": 7987839,
    "node_id": "MDc6UmVsZWFzZTc5ODc4Mzk=",
    "tag_name": "1.3.0",
    "target_commitish": "master",
    "name": "Version 1.3.0",
    "draft": false,
    "author": {
      "login": "housseindjirdeh",
      "id": 12476932,
      "node_id": "MDQ6VXNlcjEyNDc2OTMy",
      "avatar_url": "https://avatars3.githubusercontent.com/u/12476932?v=4",
      "gravatar_id": "",
      "url": "https://api.github.com/users/housseindjirdeh",
      "html_url": "https://github.com/housseindjirdeh",
      "followers_url": "https://api.github.com/users/housseindjirdeh/followers",
      "following_url": "https://api.github.com/users/housseindjirdeh/following{/other_user}",
      "gists_url": "https://api.github.com/users/housseindjirdeh/gists{/gist_id}",
      "starred_url": "https://api.github.com/users/housseindjirdeh/starred{/owner}{/repo}",
      "subscriptions_url": "https://api.github.com/users/housseindjirdeh/subscriptions",
      "organizations_url": "https://api.github.com/users/housseindjirdeh/orgs",
      "repos_url": "https://api.github.com/users/housseindjirdeh/repos",
      "events_url": "https://api.github.com/users/housseindjirdeh/events{/privacy}",
      "received_events_url": "https://api.github.com/users/housseindjirdeh/received_events",
      "type": "User",
      "site_admin": false
    },
    "prerelease": false,
    "created_at": "2017-10-04T03:09:33Z",
    "published_at": "2017-10-04T03:36:33Z",
    "assets": [
      {
        "url": "https://api.github.com/repos/gitpoint/git-point/releases/assets/4977760",
        "id": 4977760,
        "node_id": "MDEyOlJlbGVhc2VBc3NldDQ5Nzc3NjA=",
        "name": "GitPoint.apk",
        "label": null,
        "uploader": {
          "login": "housseindjirdeh",
          "id": 12476932,
          "node_id": "MDQ6VXNlcjEyNDc2OTMy",
          "avatar_url": "https://avatars3.githubusercontent.com/u/12476932?v=4",
          "gravatar_id": "",
          "url": "https://api.github.com/users/housseindjirdeh",
          "html_url": "https://github.com/housseindjirdeh",
          "followers_url": "https://api.github.com/users/housseindjirdeh/followers",
          "following_url": "https://api.github.com/users/housseindjirdeh/following{/other_user}",
          "gists_url": "https://api.github.com/users/housseindjirdeh/gists{/gist_id}",
          "starred_url": "https://api.github.com/users/housseindjirdeh/starred{/owner}{/repo}",
          "subscriptions_url": "https://api.github.com/users/housseindjirdeh/subscriptions",
          "organizations_url": "https://api.github.com/users/housseindjirdeh/orgs",
          "repos_url": "https://api.github.com/users/housseindjirdeh/repos",
          "events_url": "https://api.github.com/users/housseindjirdeh/events{/privacy}",
          "received_events_url": "https://api.github.com/users/housseindjirdeh/received_events",
          "type": "User",
          "site_admin": false
        },
        "content_type": "application/vnd.android.package-archive",
        "state": "uploaded",
        "size": 9777458,
        "download_count": 10,
        "created_at": "2017-10-04T03:42:07Z",
        "updated_at": "2017-10-04T03:42:30Z",
        "browser_download_url": "https://github.com/gitpoint/git-point/releases/download/1.3.0/GitPoint.apk"
      }
    ],
    "tarball_url": "https://api.github.com/repos/gitpoint/git-point/tarball/1.3.0",
    "zipball_url": "https://api.github.com/repos/gitpoint/git-point/zipball/1.3.0",
    "body": "This version is jam packed with some really sweet treats, including but not limited to:  \r\n\r\n• Ability to select from six different languages \r\n• You can now edit issue comments\r\n• Brand new font\r\n• Images and GIFs render perfectly within issue comments\r\n• Icon that shows how many unread notifications you have as well as more control to clear them\r\n• Comment counts show beside every issue list item\r\n• READMEs now show with correct formatting and design\r\n• Sign out functionality works smoothly without authentication details remaining cached\r\n• UI improvements and bug fixes throughout\r\n\r\nAnd we're just getting warmed up!"
  },
  {
    "url": "https://api.github.com/repos/gitpoint/git-point/releases/7295830",
    "assets_url": "https://api.github.com/repos/gitpoint/git-point/releases/7295830/assets",
    "upload_url": "https://uploads.github.com/repos/gitpoint/git-point/releases/7295830/assets{?name,label}",
    "html_url": "https://github.com/gitpoint/git-point/releases/tag/1.1.0",
    "id": 7295830,
    "node_id": "MDc6UmVsZWFzZTcyOTU4MzA=",
    "tag_name": "1.1.0",
    "target_commitish": "master",
    "name": "Version 1.1.0",
    "draft": false,
    "author": {
      "login": "housseindjirdeh",
      "id": 12476932,
      "node_id": "MDQ6VXNlcjEyNDc2OTMy",
      "avatar_url": "https://avatars3.githubusercontent.com/u/12476932?v=4",
      "gravatar_id": "",
      "url": "https://api.github.com/users/housseindjirdeh",
      "html_url": "https://github.com/housseindjirdeh",
      "followers_url": "https://api.github.com/users/housseindjirdeh/followers",
      "following_url": "https://api.github.com/users/housseindjirdeh/following{/other_user}",
      "gists_url": "https://api.github.com/users/housseindjirdeh/gists{/gist_id}",
      "starred_url": "https://api.github.com/users/housseindjirdeh/starred{/owner}{/repo}",
      "subscriptions_url": "https://api.github.com/users/housseindjirdeh/subscriptions",
      "organizations_url": "https://api.github.com/users/housseindjirdeh/orgs",
      "repos_url": "https://api.github.com/users/housseindjirdeh/repos",
      "events_url": "https://api.github.com/users/housseindjirdeh/events{/privacy}",
      "received_events_url": "https://api.github.com/users/housseindjirdeh/received_events",
      "type": "User",
      "site_admin": false
    },
    "prerelease": false,
    "created_at": "2017-08-06T04:30:31Z",
    "published_at": "2017-08-06T04:13:06Z",
    "assets": [
      {
        "url": "https://api.github.com/repos/gitpoint/git-point/releases/assets/4512867",
        "id": 4512867,
        "node_id": "MDEyOlJlbGVhc2VBc3NldDQ1MTI4Njc=",
        "name": "GitPoint.apk",
        "label": null,
        "uploader": {
          "login": "housseindjirdeh",
          "id": 12476932,
          "node_id": "MDQ6VXNlcjEyNDc2OTMy",
          "avatar_url": "https://avatars3.githubusercontent.com/u/12476932?v=4",
          "gravatar_id": "",
          "url": "https://api.github.com/users/housseindjirdeh",
          "html_url": "https://github.com/housseindjirdeh",
          "followers_url": "https://api.github.com/users/housseindjirdeh/followers",
          "following_url": "https://api.github.com/users/housseindjirdeh/following{/other_user}",
          "gists_url": "https://api.github.com/users/housseindjirdeh/gists{/gist_id}",
          "starred_url": "https://api.github.com/users/housseindjirdeh/starred{/owner}{/repo}",
          "subscriptions_url": "https://api.github.com/users/housseindjirdeh/subscriptions",
          "organizations_url": "https://api.github.com/users/housseindjirdeh/orgs",
          "repos_url": "https://api.github.com/users/housseindjirdeh/repos",
          "events_url": "https://api.github.com/users/housseindjirdeh/events{/privacy}",
          "received_events_url": "https://api.github.com/users/housseindjirdeh/received_events",
          "type": "User",
          "site_admin": false
        },
        "content_type": "application/vnd.android.package-archive",
        "state": "uploaded",
        "size": 9788131,
        "download_count": 22,
        "created_at": "2017-08-06T04:20:32Z",
        "updated_at": "2017-08-06T04:20:40Z",
        "browser_download_url": "https://github.com/gitpoint/git-point/releases/download/1.1.0/GitPoint.apk"
      },
      {
        "url": "https://api.github.com/repos/gitpoint/git-point/releases/assets/4512868",
        "id": 4512868,
        "node_id": "MDEyOlJlbGVhc2VBc3NldDQ1MTI4Njg=",
        "name": "GitPoint.ipa",
        "label": null,
        "uploader": {
          "login": "housseindjirdeh",
          "id": 12476932,
          "node_id": "MDQ6VXNlcjEyNDc2OTMy",
          "avatar_url": "https://avatars3.githubusercontent.com/u/12476932?v=4",
          "gravatar_id": "",
          "url": "https://api.github.com/users/housseindjirdeh",
          "html_url": "https://github.com/housseindjirdeh",
          "followers_url": "https://api.github.com/users/housseindjirdeh/followers",
          "following_url": "https://api.github.com/users/housseindjirdeh/following{/other_user}",
          "gists_url": "https://api.github.com/users/housseindjirdeh/gists{/gist_id}",
          "starred_url": "https://api.github.com/users/housseindjirdeh/starred{/owner}{/repo}",
          "subscriptions_url": "https://api.github.com/users/housseindjirdeh/subscriptions",
          "organizations_url": "https://api.github.com/users/housseindjirdeh/orgs",
          "repos_url": "https://api.github.com/users/housseindjirdeh/repos",
          "events_url": "https://api.github.com/users/housseindjirdeh/events{/privacy}",
          "received_events_url": "https://api.github.com/users/housseindjirdeh/received_events",
          "type": "User",
          "site_admin": false
        },
        "content_type": "application/octet-stream",
        "state": "uploaded",
        "size": 10942643,
        "download_count": 8,
        "created_at": "2017-08-06T04:20:46Z",
        "updated_at": "2017-08-06T04:20:55Z",
        "browser_download_url": "https://github.com/gitpoint/git-point/releases/download/1.1.0/GitPoint.ipa"
      }
    ],
    "tarball_url": "https://api.github.com/repos/gitpoint/git-point/tarball/1.1.0",
    "zipball_url": "https://api.github.com/repos/gitpoint/git-point/zipball/1.1.0",
    "body": "Suite of updates including main Android release build with the addition of removing unused permissions (1.0 was original Android launch).\r\n\r\nNote: Current iOS App Store version of app is `v1.2` and this slight discrepancy is due to the iOS release happening a few weeks sooner than Android. The next release will streamline this by bumping both platform versions to `1.3`.\r\n\r\nWill also keep things to the third degree with semantic versioning (`1.3.0`) on both platforms (`versionName`: Android and `build.gradle` in iOS) and package.json starting from the next release."
  }
]
